{"courses_dept":"japn","courses_title":"begin japn ii","courses_id":"103","courses_avg":66.68,"courses_instructor":"kim, ihhwa","courses_pass":18,"courses_fail":1,"courses_audit":1,"courses_uuid":63,"courses_year":"2009"}{"courses_dept":"japn","courses_title":"begin japn ii","courses_id":"103","courses_avg":72.46,"courses_instructor":"kim, ihhwa","courses_pass":24,"courses_fail":0,"courses_audit":0,"courses_uuid":64,"courses_year":"2009"}{"courses_dept":"japn","courses_title":"begin japn ii","courses_id":"103","courses_avg":72.96,"courses_instructor":"kim, ihhwa","courses_pass":24,"courses_fail":2,"courses_audit":0,"courses_uuid":65,"courses_year":"2009"}{"courses_dept":"japn","courses_title":"begin japn ii","courses_id":"103","courses_avg":72.91,"courses_instructor":"kim, ihhwa","courses_pass":21,"courses_fail":2,"courses_audit":0,"courses_uuid":66,"courses_year":"2009"}{"courses_dept":"japn","courses_title":"begin japn ii","courses_id":"103","courses_avg":75.1,"courses_instructor":"fan, belen","courses_pass":10,"courses_fail":0,"courses_audit":1,"courses_uuid":67,"courses_year":"2009"}{"courses_dept":"japn","courses_title":"begin japn ii","courses_id":"103","courses_avg":71.53,"courses_instructor":"fan, belen","courses_pass":18,"courses_fail":1,"courses_audit":2,"courses_uuid":68,"courses_year":"2009"}{"courses_dept":"japn","courses_title":"begin japn ii","courses_id":"103","courses_avg":71.82,"courses_instructor":"","courses_pass":115,"courses_fail":6,"courses_audit":4,"courses_uuid":69,"courses_year":1900}{"courses_dept":"japn","courses_title":"begin japn ii","courses_id":"103","courses_avg":71.6,"courses_instructor":"ode, maki","courses_pass":15,"courses_fail":0,"courses_audit":0,"courses_uuid":12303,"courses_year":"2012"}{"courses_dept":"japn","courses_title":"begin japn ii","courses_id":"103","courses_avg":64.88,"courses_instructor":"ode, maki","courses_pass":15,"courses_fail":2,"courses_audit":1,"courses_uuid":12304,"courses_year":"2012"}{"courses_dept":"japn","courses_title":"begin japn ii","courses_id":"103","courses_avg":76.76,"courses_instructor":"tsuda, asami","courses_pass":21,"courses_fail":0,"courses_audit":0,"courses_uuid":12305,"courses_year":"2012"}{"courses_dept":"japn","courses_title":"begin japn ii","courses_id":"103","courses_avg":75.06,"courses_instructor":"tsuda, asami","courses_pass":16,"courses_fail":0,"courses_audit":0,"courses_uuid":12306,"courses_year":"2012"}{"courses_dept":"japn","courses_title":"begin japn ii","courses_id":"103","courses_avg":81.13,"courses_instructor":"yonemoto, kazuhiro","courses_pass":15,"courses_fail":0,"courses_audit":0,"courses_uuid":12307,"courses_year":"2012"}{"courses_dept":"japn","courses_title":"begin japn ii","courses_id":"103","courses_avg":78.7,"courses_instructor":"tsuda, asami","courses_pass":10,"courses_fail":0,"courses_audit":0,"courses_uuid":12308,"courses_year":"2012"}{"courses_dept":"japn","courses_title":"begin japn ii","courses_id":"103","courses_avg":74.4,"courses_instructor":"","courses_pass":92,"courses_fail":2,"courses_audit":1,"courses_uuid":12309,"courses_year":1900}{"courses_dept":"japn","courses_title":"begin japn ii","courses_id":"103","courses_avg":75,"courses_instructor":"nakata, masahiko","courses_pass":19,"courses_fail":0,"courses_audit":0,"courses_uuid":15027,"courses_year":"2009"}{"courses_dept":"japn","courses_title":"begin japn ii","courses_id":"103","courses_avg":75,"courses_instructor":"","courses_pass":19,"courses_fail":0,"courses_audit":0,"courses_uuid":15028,"courses_year":1900}{"courses_dept":"japn","courses_title":"begin japn ii","courses_id":"103","courses_avg":68.71,"courses_instructor":"ode, maki","courses_pass":14,"courses_fail":0,"courses_audit":1,"courses_uuid":26861,"courses_year":"2013"}{"courses_dept":"japn","courses_title":"begin japn ii","courses_id":"103","courses_avg":69.33,"courses_instructor":"ode, maki","courses_pass":22,"courses_fail":2,"courses_audit":0,"courses_uuid":26862,"courses_year":"2013"}{"courses_dept":"japn","courses_title":"begin japn ii","courses_id":"103","courses_avg":74.29,"courses_instructor":"kazama, misuzu","courses_pass":21,"courses_fail":0,"courses_audit":0,"courses_uuid":26863,"courses_year":"2013"}{"courses_dept":"japn","courses_title":"begin japn ii","courses_id":"103","courses_avg":68.29,"courses_instructor":"nakata, masahiko","courses_pass":17,"courses_fail":0,"courses_audit":0,"courses_uuid":26864,"courses_year":"2013"}{"courses_dept":"japn","courses_title":"begin japn ii","courses_id":"103","courses_avg":73,"courses_instructor":"yonemoto, kazuhiro","courses_pass":20,"courses_fail":0,"courses_audit":0,"courses_uuid":26865,"courses_year":"2013"}{"courses_dept":"japn","courses_title":"begin japn ii","courses_id":"103","courses_avg":70.91,"courses_instructor":"","courses_pass":94,"courses_fail":2,"courses_audit":1,"courses_uuid":26866,"courses_year":1900}{"courses_dept":"japn","courses_title":"begin japn ii","courses_id":"103","courses_avg":71.9,"courses_instructor":"ode, maki","courses_pass":10,"courses_fail":0,"courses_audit":1,"courses_uuid":32561,"courses_year":"2012"}{"courses_dept":"japn","courses_title":"begin japn ii","courses_id":"103","courses_avg":71.9,"courses_instructor":"","courses_pass":10,"courses_fail":0,"courses_audit":1,"courses_uuid":32562,"courses_year":1900}{"courses_dept":"japn","courses_title":"begin japn ii","courses_id":"103","courses_avg":69.38,"courses_instructor":"nakata, masahiko","courses_pass":12,"courses_fail":1,"courses_audit":1,"courses_uuid":33120,"courses_year":"2014"}{"courses_dept":"japn","courses_title":"begin japn ii","courses_id":"103","courses_avg":69.38,"courses_instructor":"","courses_pass":12,"courses_fail":1,"courses_audit":1,"courses_uuid":33121,"courses_year":1900}{"courses_dept":"japn","courses_title":"begin japn ii","courses_id":"103","courses_avg":74.76,"courses_instructor":"kim, ihhwa","courses_pass":25,"courses_fail":0,"courses_audit":0,"courses_uuid":41977,"courses_year":"2007"}{"courses_dept":"japn","courses_title":"begin japn ii","courses_id":"103","courses_avg":71.37,"courses_instructor":"fan, belen","courses_pass":19,"courses_fail":0,"courses_audit":0,"courses_uuid":41978,"courses_year":"2007"}{"courses_dept":"japn","courses_title":"begin japn ii","courses_id":"103","courses_avg":73.46,"courses_instructor":"kim, ihhwa","courses_pass":23,"courses_fail":1,"courses_audit":1,"courses_uuid":41979,"courses_year":"2007"}{"courses_dept":"japn","courses_title":"begin japn ii","courses_id":"103","courses_avg":73.27,"courses_instructor":"trudel, kazuko","courses_pass":22,"courses_fail":0,"courses_audit":0,"courses_uuid":41980,"courses_year":"2007"}{"courses_dept":"japn","courses_title":"begin japn ii","courses_id":"103","courses_avg":77.89,"courses_instructor":"trudel, kazuko","courses_pass":18,"courses_fail":0,"courses_audit":0,"courses_uuid":41981,"courses_year":"2007"}{"courses_dept":"japn","courses_title":"begin japn ii","courses_id":"103","courses_avg":73.93,"courses_instructor":"fan, belen","courses_pass":14,"courses_fail":0,"courses_audit":0,"courses_uuid":41982,"courses_year":"2007"}{"courses_dept":"japn","courses_title":"begin japn ii","courses_id":"103","courses_avg":74.07,"courses_instructor":"","courses_pass":121,"courses_fail":1,"courses_audit":1,"courses_uuid":41983,"courses_year":1900}{"courses_dept":"japn","courses_title":"begin japn ii","courses_id":"103","courses_avg":74.53,"courses_instructor":"","courses_pass":15,"courses_fail":0,"courses_audit":0,"courses_uuid":47498,"courses_year":"2008"}{"courses_dept":"japn","courses_title":"begin japn ii","courses_id":"103","courses_avg":74.53,"courses_instructor":"","courses_pass":15,"courses_fail":0,"courses_audit":0,"courses_uuid":47499,"courses_year":1900}{"courses_dept":"japn","courses_title":"begin japn ii","courses_id":"103","courses_avg":67.67,"courses_instructor":"kim, ihhwa","courses_pass":21,"courses_fail":0,"courses_audit":0,"courses_uuid":59889,"courses_year":"2010"}{"courses_dept":"japn","courses_title":"begin japn ii","courses_id":"103","courses_avg":67.67,"courses_instructor":"","courses_pass":21,"courses_fail":0,"courses_audit":0,"courses_uuid":59890,"courses_year":1900}{"courses_dept":"japn","courses_title":"begin japn ii","courses_id":"103","courses_avg":72.4,"courses_instructor":"","courses_pass":14,"courses_fail":1,"courses_audit":1,"courses_uuid":60845,"courses_year":"2008"}{"courses_dept":"japn","courses_title":"begin japn ii","courses_id":"103","courses_avg":72.05,"courses_instructor":"","courses_pass":22,"courses_fail":0,"courses_audit":0,"courses_uuid":60846,"courses_year":"2008"}{"courses_dept":"japn","courses_title":"begin japn ii","courses_id":"103","courses_avg":73.29,"courses_instructor":"","courses_pass":21,"courses_fail":0,"courses_audit":0,"courses_uuid":60847,"courses_year":"2008"}{"courses_dept":"japn","courses_title":"begin japn ii","courses_id":"103","courses_avg":78.63,"courses_instructor":"","courses_pass":27,"courses_fail":0,"courses_audit":0,"courses_uuid":60848,"courses_year":"2008"}{"courses_dept":"japn","courses_title":"begin japn ii","courses_id":"103","courses_avg":71.3,"courses_instructor":"","courses_pass":19,"courses_fail":1,"courses_audit":0,"courses_uuid":60849,"courses_year":"2008"}{"courses_dept":"japn","courses_title":"begin japn ii","courses_id":"103","courses_avg":75.05,"courses_instructor":"","courses_pass":18,"courses_fail":1,"courses_audit":0,"courses_uuid":60850,"courses_year":"2008"}{"courses_dept":"japn","courses_title":"begin japn ii","courses_id":"103","courses_avg":74.07,"courses_instructor":"","courses_pass":121,"courses_fail":3,"courses_audit":1,"courses_uuid":60851,"courses_year":1900}{"courses_dept":"japn","courses_title":"begin japn ii","courses_id":"103","courses_avg":68.23,"courses_instructor":"watai, fumiko","courses_pass":20,"courses_fail":2,"courses_audit":0,"courses_uuid":61325,"courses_year":"2011"}{"courses_dept":"japn","courses_title":"begin japn ii","courses_id":"103","courses_avg":68.23,"courses_instructor":"","courses_pass":20,"courses_fail":2,"courses_audit":0,"courses_uuid":61326,"courses_year":1900}{"courses_dept":"japn","courses_title":"begin japn ii","courses_id":"103","courses_avg":69,"courses_instructor":"","courses_pass":17,"courses_fail":0,"courses_audit":1,"courses_uuid":66916,"courses_year":"2010"}{"courses_dept":"japn","courses_title":"begin japn ii","courses_id":"103","courses_avg":72.44,"courses_instructor":"watai, fumiko","courses_pass":18,"courses_fail":0,"courses_audit":0,"courses_uuid":66917,"courses_year":"2010"}{"courses_dept":"japn","courses_title":"begin japn ii","courses_id":"103","courses_avg":67.63,"courses_instructor":"watai, fumiko","courses_pass":15,"courses_fail":1,"courses_audit":0,"courses_uuid":66918,"courses_year":"2010"}{"courses_dept":"japn","courses_title":"begin japn ii","courses_id":"103","courses_avg":73.7,"courses_instructor":"kim, ihhwa","courses_pass":23,"courses_fail":0,"courses_audit":0,"courses_uuid":66919,"courses_year":"2010"}{"courses_dept":"japn","courses_title":"begin japn ii","courses_id":"103","courses_avg":69.22,"courses_instructor":"kim, ihhwa","courses_pass":9,"courses_fail":0,"courses_audit":1,"courses_uuid":66920,"courses_year":"2010"}{"courses_dept":"japn","courses_title":"begin japn ii","courses_id":"103","courses_avg":71.57,"courses_instructor":"kim, ihhwa","courses_pass":14,"courses_fail":0,"courses_audit":0,"courses_uuid":66921,"courses_year":"2010"}{"courses_dept":"japn","courses_title":"begin japn ii","courses_id":"103","courses_avg":70.92,"courses_instructor":"","courses_pass":96,"courses_fail":1,"courses_audit":2,"courses_uuid":66922,"courses_year":1900}{"courses_dept":"japn","courses_title":"begin japn ii","courses_id":"103","courses_avg":72.64,"courses_instructor":"ode, maki","courses_pass":13,"courses_fail":1,"courses_audit":0,"courses_uuid":73724,"courses_year":"2013"}{"courses_dept":"japn","courses_title":"begin japn ii","courses_id":"103","courses_avg":72.64,"courses_instructor":"","courses_pass":13,"courses_fail":1,"courses_audit":0,"courses_uuid":73725,"courses_year":1900}{"courses_dept":"japn","courses_title":"begin japn ii","courses_id":"103","courses_avg":66.83,"courses_instructor":"","courses_pass":6,"courses_fail":0,"courses_audit":0,"courses_uuid":82499,"courses_year":"2011"}{"courses_dept":"japn","courses_title":"begin japn ii","courses_id":"103","courses_avg":72.05,"courses_instructor":"ode, maki","courses_pass":21,"courses_fail":0,"courses_audit":1,"courses_uuid":82500,"courses_year":"2011"}{"courses_dept":"japn","courses_title":"begin japn ii","courses_id":"103","courses_avg":73.82,"courses_instructor":"tsuda, asami","courses_pass":17,"courses_fail":0,"courses_audit":0,"courses_uuid":82501,"courses_year":"2011"}{"courses_dept":"japn","courses_title":"begin japn ii","courses_id":"103","courses_avg":75.37,"courses_instructor":"tsuda, asami","courses_pass":19,"courses_fail":0,"courses_audit":1,"courses_uuid":82502,"courses_year":"2011"}{"courses_dept":"japn","courses_title":"begin japn ii","courses_id":"103","courses_avg":70.6,"courses_instructor":"watai, fumiko","courses_pass":10,"courses_fail":0,"courses_audit":2,"courses_uuid":82503,"courses_year":"2011"}{"courses_dept":"japn","courses_title":"begin japn ii","courses_id":"103","courses_avg":77.75,"courses_instructor":"tsuda, asami","courses_pass":12,"courses_fail":0,"courses_audit":0,"courses_uuid":82504,"courses_year":"2011"}{"courses_dept":"japn","courses_title":"begin japn ii","courses_id":"103","courses_avg":73.41,"courses_instructor":"","courses_pass":85,"courses_fail":0,"courses_audit":4,"courses_uuid":82505,"courses_year":1900}{"courses_dept":"japn","courses_title":"begin japn ii","courses_id":"103","courses_avg":69.36,"courses_instructor":"nakata, masahiko","courses_pass":25,"courses_fail":0,"courses_audit":0,"courses_uuid":93544,"courses_year":"2015"}{"courses_dept":"japn","courses_title":"begin japn ii","courses_id":"103","courses_avg":69.75,"courses_instructor":"nakata, masahiko","courses_pass":22,"courses_fail":2,"courses_audit":1,"courses_uuid":93545,"courses_year":"2015"}{"courses_dept":"japn","courses_title":"begin japn ii","courses_id":"103","courses_avg":76.77,"courses_instructor":"koizumi, keiko","courses_pass":13,"courses_fail":0,"courses_audit":0,"courses_uuid":93546,"courses_year":"2015"}{"courses_dept":"japn","courses_title":"begin japn ii","courses_id":"103","courses_avg":67.63,"courses_instructor":"koizumi, keiko","courses_pass":16,"courses_fail":0,"courses_audit":0,"courses_uuid":93547,"courses_year":"2015"}{"courses_dept":"japn","courses_title":"begin japn ii","courses_id":"103","courses_avg":73.48,"courses_instructor":"kim, ihhwa","courses_pass":22,"courses_fail":1,"courses_audit":0,"courses_uuid":93548,"courses_year":"2015"}{"courses_dept":"japn","courses_title":"begin japn ii","courses_id":"103","courses_avg":71.07,"courses_instructor":"","courses_pass":98,"courses_fail":3,"courses_audit":1,"courses_uuid":93549,"courses_year":1900}{"courses_dept":"japn","courses_title":"begin japn ii","courses_id":"103","courses_avg":69.33,"courses_instructor":"","courses_pass":9,"courses_fail":0,"courses_audit":0,"courses_uuid":98137,"courses_year":"2014"}{"courses_dept":"japn","courses_title":"begin japn ii","courses_id":"103","courses_avg":72.73,"courses_instructor":"ode, maki","courses_pass":15,"courses_fail":0,"courses_audit":1,"courses_uuid":98138,"courses_year":"2014"}{"courses_dept":"japn","courses_title":"begin japn ii","courses_id":"103","courses_avg":78.52,"courses_instructor":"","courses_pass":25,"courses_fail":0,"courses_audit":0,"courses_uuid":98139,"courses_year":"2014"}{"courses_dept":"japn","courses_title":"begin japn ii","courses_id":"103","courses_avg":76.08,"courses_instructor":"","courses_pass":25,"courses_fail":1,"courses_audit":0,"courses_uuid":98140,"courses_year":"2014"}{"courses_dept":"japn","courses_title":"begin japn ii","courses_id":"103","courses_avg":70.14,"courses_instructor":"fan, belen","courses_pass":14,"courses_fail":0,"courses_audit":0,"courses_uuid":98141,"courses_year":"2014"}{"courses_dept":"japn","courses_title":"begin japn ii","courses_id":"103","courses_avg":78.33,"courses_instructor":"","courses_pass":6,"courses_fail":0,"courses_audit":0,"courses_uuid":98142,"courses_year":"2014"}{"courses_dept":"japn","courses_title":"begin japn ii","courses_id":"103","courses_avg":74.82,"courses_instructor":"","courses_pass":94,"courses_fail":1,"courses_audit":1,"courses_uuid":98143,"courses_year":1900}