{"courses_dept":"arth","courses_title":"eur arch","courses_id":"346","courses_avg":72.51,"courses_instructor":"carr, geoffrey","courses_pass":67,"courses_fail":3,"courses_audit":1,"courses_uuid":8577,"courses_year":"2014"}{"courses_dept":"arth","courses_title":"eur arch","courses_id":"346","courses_avg":72.51,"courses_instructor":"","courses_pass":67,"courses_fail":3,"courses_audit":1,"courses_uuid":8578,"courses_year":1900}{"courses_dept":"arth","courses_title":"eur arch","courses_id":"346","courses_avg":71.17,"courses_instructor":"windsor-liscombe, rhodri","courses_pass":57,"courses_fail":8,"courses_audit":0,"courses_uuid":10982,"courses_year":"2007"}{"courses_dept":"arth","courses_title":"eur arch","courses_id":"346","courses_avg":71.17,"courses_instructor":"","courses_pass":57,"courses_fail":8,"courses_audit":0,"courses_uuid":10983,"courses_year":1900}{"courses_dept":"arth","courses_title":"eur arch","courses_id":"346","courses_avg":78.45,"courses_instructor":"windsor-liscombe, rhodri","courses_pass":55,"courses_fail":0,"courses_audit":0,"courses_uuid":74080,"courses_year":"2011"}{"courses_dept":"arth","courses_title":"eur arch","courses_id":"346","courses_avg":78.45,"courses_instructor":"","courses_pass":55,"courses_fail":0,"courses_audit":0,"courses_uuid":74081,"courses_year":1900}{"courses_dept":"arth","courses_title":"eur arch","courses_id":"346","courses_avg":76.94,"courses_instructor":"windsor-liscombe, rhodri","courses_pass":65,"courses_fail":0,"courses_audit":0,"courses_uuid":91296,"courses_year":"2009"}{"courses_dept":"arth","courses_title":"eur arch","courses_id":"346","courses_avg":76.94,"courses_instructor":"","courses_pass":65,"courses_fail":0,"courses_audit":0,"courses_uuid":91297,"courses_year":1900}{"courses_dept":"arth","courses_title":"eur arch","courses_id":"346","courses_avg":73.43,"courses_instructor":"carr, geoffrey","courses_pass":52,"courses_fail":4,"courses_audit":1,"courses_uuid":98432,"courses_year":"2015"}{"courses_dept":"arth","courses_title":"eur arch","courses_id":"346","courses_avg":73.43,"courses_instructor":"","courses_pass":52,"courses_fail":4,"courses_audit":1,"courses_uuid":98433,"courses_year":1900}