{"courses_dept":"apbi","courses_title":"sustain agr&food","courses_id":"265","courses_avg":86.14,"courses_instructor":"lewis, delisa","courses_pass":28,"courses_fail":0,"courses_audit":0,"courses_uuid":24521,"courses_year":"2013"}{"courses_dept":"apbi","courses_title":"sustain agr&food","courses_id":"265","courses_avg":86.14,"courses_instructor":"","courses_pass":28,"courses_fail":0,"courses_audit":0,"courses_uuid":24522,"courses_year":1900}{"courses_dept":"apbi","courses_title":"sustain agr&food","courses_id":"265","courses_avg":89.29,"courses_instructor":"lewis, delisa ann","courses_pass":21,"courses_fail":0,"courses_audit":0,"courses_uuid":32433,"courses_year":"2015"}{"courses_dept":"apbi","courses_title":"sustain agr&food","courses_id":"265","courses_avg":89.29,"courses_instructor":"","courses_pass":21,"courses_fail":0,"courses_audit":0,"courses_uuid":32434,"courses_year":1900}{"courses_dept":"apbi","courses_title":"sustain agr&food","courses_id":"265","courses_avg":86.57,"courses_instructor":"lewis, delisa","courses_pass":23,"courses_fail":0,"courses_audit":0,"courses_uuid":87318,"courses_year":"2014"}{"courses_dept":"apbi","courses_title":"sustain agr&food","courses_id":"265","courses_avg":86.57,"courses_instructor":"","courses_pass":23,"courses_fail":0,"courses_audit":0,"courses_uuid":87319,"courses_year":1900}