{"courses_dept":"hist","courses_title":"inventing canada","courses_id":"324","courses_avg":68.06,"courses_instructor":"","courses_pass":48,"courses_fail":2,"courses_audit":0,"courses_uuid":13505,"courses_year":"2008"}{"courses_dept":"hist","courses_title":"inventing canada","courses_id":"324","courses_avg":68.06,"courses_instructor":"","courses_pass":48,"courses_fail":2,"courses_audit":0,"courses_uuid":13506,"courses_year":1900}{"courses_dept":"hist","courses_title":"inventing canada","courses_id":"324","courses_avg":71.67,"courses_instructor":"miller, bradley","courses_pass":36,"courses_fail":0,"courses_audit":0,"courses_uuid":29530,"courses_year":"2015"}{"courses_dept":"hist","courses_title":"inventing canada","courses_id":"324","courses_avg":71.67,"courses_instructor":"","courses_pass":36,"courses_fail":0,"courses_audit":0,"courses_uuid":29531,"courses_year":1900}{"courses_dept":"hist","courses_title":"inventing canada","courses_id":"324","courses_avg":72.76,"courses_instructor":"lennox, jeffers","courses_pass":41,"courses_fail":1,"courses_audit":0,"courses_uuid":48759,"courses_year":"2011"}{"courses_dept":"hist","courses_title":"inventing canada","courses_id":"324","courses_avg":72.76,"courses_instructor":"","courses_pass":41,"courses_fail":1,"courses_audit":0,"courses_uuid":48760,"courses_year":1900}{"courses_dept":"hist","courses_title":"inventing canada","courses_id":"324","courses_avg":72.33,"courses_instructor":"lennox, jeffers","courses_pass":39,"courses_fail":0,"courses_audit":0,"courses_uuid":61730,"courses_year":"2010"}{"courses_dept":"hist","courses_title":"inventing canada","courses_id":"324","courses_avg":72.33,"courses_instructor":"","courses_pass":39,"courses_fail":0,"courses_audit":0,"courses_uuid":61731,"courses_year":1900}{"courses_dept":"hist","courses_title":"inventing canada","courses_id":"324","courses_avg":73.23,"courses_instructor":"grittner, colin","courses_pass":43,"courses_fail":0,"courses_audit":0,"courses_uuid":66671,"courses_year":"2016"}{"courses_dept":"hist","courses_title":"inventing canada","courses_id":"324","courses_avg":73.23,"courses_instructor":"","courses_pass":43,"courses_fail":0,"courses_audit":0,"courses_uuid":66672,"courses_year":1900}{"courses_dept":"hist","courses_title":"inventing canada","courses_id":"324","courses_avg":71.03,"courses_instructor":"miller, bradley","courses_pass":35,"courses_fail":1,"courses_audit":0,"courses_uuid":85436,"courses_year":"2014"}{"courses_dept":"hist","courses_title":"inventing canada","courses_id":"324","courses_avg":71.03,"courses_instructor":"","courses_pass":35,"courses_fail":1,"courses_audit":0,"courses_uuid":85437,"courses_year":1900}{"courses_dept":"hist","courses_title":"inventing canada","courses_id":"324","courses_avg":71.17,"courses_instructor":"miller, bradley","courses_pass":29,"courses_fail":0,"courses_audit":1,"courses_uuid":96000,"courses_year":"2013"}{"courses_dept":"hist","courses_title":"inventing canada","courses_id":"324","courses_avg":71.17,"courses_instructor":"","courses_pass":29,"courses_fail":0,"courses_audit":1,"courses_uuid":96001,"courses_year":1900}