{"courses_dept":"etec","courses_title":"plan man learn","courses_id":"520","courses_avg":87.35,"courses_instructor":"bullen, mark","courses_pass":17,"courses_fail":0,"courses_audit":0,"courses_uuid":16396,"courses_year":"2011"}{"courses_dept":"etec","courses_title":"plan man learn","courses_id":"520","courses_avg":85.67,"courses_instructor":"bourlova, tatiana","courses_pass":15,"courses_fail":0,"courses_audit":0,"courses_uuid":16397,"courses_year":"2011"}{"courses_dept":"etec","courses_title":"plan man learn","courses_id":"520","courses_avg":86.56,"courses_instructor":"","courses_pass":32,"courses_fail":0,"courses_audit":0,"courses_uuid":16398,"courses_year":1900}{"courses_dept":"etec","courses_title":"plan man learn","courses_id":"520","courses_avg":86.44,"courses_instructor":"bullen, mark","courses_pass":16,"courses_fail":0,"courses_audit":0,"courses_uuid":16969,"courses_year":"2014"}{"courses_dept":"etec","courses_title":"plan man learn","courses_id":"520","courses_avg":89.93,"courses_instructor":"bourlova, tatiana","courses_pass":15,"courses_fail":0,"courses_audit":0,"courses_uuid":16970,"courses_year":"2014"}{"courses_dept":"etec","courses_title":"plan man learn","courses_id":"520","courses_avg":88.13,"courses_instructor":"","courses_pass":31,"courses_fail":0,"courses_audit":0,"courses_uuid":16971,"courses_year":1900}{"courses_dept":"etec","courses_title":"plan man learn","courses_id":"520","courses_avg":85.93,"courses_instructor":"bullen, mark","courses_pass":15,"courses_fail":0,"courses_audit":0,"courses_uuid":35024,"courses_year":"2009"}{"courses_dept":"etec","courses_title":"plan man learn","courses_id":"520","courses_avg":85.4,"courses_instructor":"bourlova, tatiana","courses_pass":5,"courses_fail":0,"courses_audit":0,"courses_uuid":35025,"courses_year":"2009"}{"courses_dept":"etec","courses_title":"plan man learn","courses_id":"520","courses_avg":85.8,"courses_instructor":"","courses_pass":20,"courses_fail":0,"courses_audit":0,"courses_uuid":35026,"courses_year":1900}{"courses_dept":"etec","courses_title":"plan man learn","courses_id":"520","courses_avg":81.41,"courses_instructor":"bullen, mark","courses_pass":17,"courses_fail":0,"courses_audit":0,"courses_uuid":39844,"courses_year":"2015"}{"courses_dept":"etec","courses_title":"plan man learn","courses_id":"520","courses_avg":87.36,"courses_instructor":"bourlova, tatiana","courses_pass":11,"courses_fail":0,"courses_audit":0,"courses_uuid":39845,"courses_year":"2015"}{"courses_dept":"etec","courses_title":"plan man learn","courses_id":"520","courses_avg":83.75,"courses_instructor":"","courses_pass":28,"courses_fail":0,"courses_audit":0,"courses_uuid":39846,"courses_year":1900}{"courses_dept":"etec","courses_title":"plan man learn","courses_id":"520","courses_avg":86.94,"courses_instructor":"bullen, mark","courses_pass":16,"courses_fail":0,"courses_audit":0,"courses_uuid":45902,"courses_year":"2012"}{"courses_dept":"etec","courses_title":"plan man learn","courses_id":"520","courses_avg":88,"courses_instructor":"bourlova, tatiana","courses_pass":14,"courses_fail":0,"courses_audit":0,"courses_uuid":45903,"courses_year":"2012"}{"courses_dept":"etec","courses_title":"plan man learn","courses_id":"520","courses_avg":87.43,"courses_instructor":"","courses_pass":30,"courses_fail":0,"courses_audit":0,"courses_uuid":45904,"courses_year":1900}{"courses_dept":"etec","courses_title":"plan man learn","courses_id":"520","courses_avg":86.68,"courses_instructor":"bullen, mark","courses_pass":22,"courses_fail":0,"courses_audit":0,"courses_uuid":70502,"courses_year":"2010"}{"courses_dept":"etec","courses_title":"plan man learn","courses_id":"520","courses_avg":89.79,"courses_instructor":"bourlova, tatiana","courses_pass":24,"courses_fail":0,"courses_audit":0,"courses_uuid":70503,"courses_year":"2010"}{"courses_dept":"etec","courses_title":"plan man learn","courses_id":"520","courses_avg":88.3,"courses_instructor":"","courses_pass":46,"courses_fail":0,"courses_audit":0,"courses_uuid":70504,"courses_year":1900}{"courses_dept":"etec","courses_title":"plan man learn","courses_id":"520","courses_avg":82.67,"courses_instructor":"bullen, mark","courses_pass":21,"courses_fail":0,"courses_audit":0,"courses_uuid":76467,"courses_year":"2013"}{"courses_dept":"etec","courses_title":"plan man learn","courses_id":"520","courses_avg":87.78,"courses_instructor":"bourlova, tatiana","courses_pass":18,"courses_fail":0,"courses_audit":0,"courses_uuid":76468,"courses_year":"2013"}{"courses_dept":"etec","courses_title":"plan man learn","courses_id":"520","courses_avg":85.03,"courses_instructor":"","courses_pass":39,"courses_fail":0,"courses_audit":0,"courses_uuid":76469,"courses_year":1900}{"courses_dept":"etec","courses_title":"plan man learn","courses_id":"520","courses_avg":85.39,"courses_instructor":"","courses_pass":23,"courses_fail":0,"courses_audit":0,"courses_uuid":92120,"courses_year":"2008"}{"courses_dept":"etec","courses_title":"plan man learn","courses_id":"520","courses_avg":87.08,"courses_instructor":"","courses_pass":25,"courses_fail":0,"courses_audit":0,"courses_uuid":92121,"courses_year":"2008"}{"courses_dept":"etec","courses_title":"plan man learn","courses_id":"520","courses_avg":86.27,"courses_instructor":"","courses_pass":48,"courses_fail":0,"courses_audit":0,"courses_uuid":92122,"courses_year":1900}{"courses_dept":"etec","courses_title":"plan man learn","courses_id":"520","courses_avg":86.55,"courses_instructor":"bullen, mark","courses_pass":22,"courses_fail":0,"courses_audit":0,"courses_uuid":96822,"courses_year":"2013"}{"courses_dept":"etec","courses_title":"plan man learn","courses_id":"520","courses_avg":86.55,"courses_instructor":"","courses_pass":22,"courses_fail":0,"courses_audit":0,"courses_uuid":96823,"courses_year":1900}