{"courses_dept":"econ","courses_title":"process econ dev","courses_id":"441","courses_avg":79.26,"courses_instructor":"francois, patrick","courses_pass":93,"courses_fail":1,"courses_audit":0,"courses_uuid":10002,"courses_year":"2016"}{"courses_dept":"econ","courses_title":"process econ dev","courses_id":"441","courses_avg":79.26,"courses_instructor":"","courses_pass":93,"courses_fail":1,"courses_audit":0,"courses_uuid":10003,"courses_year":1900}{"courses_dept":"econ","courses_title":"process econ dev","courses_id":"441","courses_avg":76.79,"courses_instructor":"eswaran, mukesh","courses_pass":34,"courses_fail":0,"courses_audit":2,"courses_uuid":11552,"courses_year":"2014"}{"courses_dept":"econ","courses_title":"process econ dev","courses_id":"441","courses_avg":76.79,"courses_instructor":"","courses_pass":34,"courses_fail":0,"courses_audit":2,"courses_uuid":11553,"courses_year":1900}{"courses_dept":"econ","courses_title":"process econ dev","courses_id":"441","courses_avg":63.77,"courses_instructor":"eswaran, mukesh","courses_pass":59,"courses_fail":11,"courses_audit":4,"courses_uuid":21546,"courses_year":"2009"}{"courses_dept":"econ","courses_title":"process econ dev","courses_id":"441","courses_avg":63.77,"courses_instructor":"","courses_pass":59,"courses_fail":11,"courses_audit":4,"courses_uuid":21547,"courses_year":1900}{"courses_dept":"econ","courses_title":"process econ dev","courses_id":"441","courses_avg":70.93,"courses_instructor":"eswaran, mukesh","courses_pass":54,"courses_fail":3,"courses_audit":4,"courses_uuid":52357,"courses_year":"2010"}{"courses_dept":"econ","courses_title":"process econ dev","courses_id":"441","courses_avg":70.93,"courses_instructor":"","courses_pass":54,"courses_fail":3,"courses_audit":4,"courses_uuid":52358,"courses_year":1900}{"courses_dept":"econ","courses_title":"process econ dev","courses_id":"441","courses_avg":66.09,"courses_instructor":"eswaran, mukesh","courses_pass":69,"courses_fail":5,"courses_audit":0,"courses_uuid":58427,"courses_year":"2007"}{"courses_dept":"econ","courses_title":"process econ dev","courses_id":"441","courses_avg":66.09,"courses_instructor":"","courses_pass":69,"courses_fail":5,"courses_audit":0,"courses_uuid":58428,"courses_year":1900}{"courses_dept":"econ","courses_title":"process econ dev","courses_id":"441","courses_avg":66.25,"courses_instructor":"","courses_pass":73,"courses_fail":7,"courses_audit":4,"courses_uuid":69887,"courses_year":"2008"}{"courses_dept":"econ","courses_title":"process econ dev","courses_id":"441","courses_avg":66.25,"courses_instructor":"","courses_pass":73,"courses_fail":7,"courses_audit":4,"courses_uuid":69888,"courses_year":1900}{"courses_dept":"econ","courses_title":"process econ dev","courses_id":"441","courses_avg":65.77,"courses_instructor":"eswaran, mukesh","courses_pass":38,"courses_fail":5,"courses_audit":0,"courses_uuid":74411,"courses_year":"2015"}{"courses_dept":"econ","courses_title":"process econ dev","courses_id":"441","courses_avg":65.77,"courses_instructor":"","courses_pass":38,"courses_fail":5,"courses_audit":0,"courses_uuid":74412,"courses_year":1900}{"courses_dept":"econ","courses_title":"process econ dev","courses_id":"441","courses_avg":66.24,"courses_instructor":"eswaran, mukesh","courses_pass":32,"courses_fail":6,"courses_audit":0,"courses_uuid":78458,"courses_year":"2012"}{"courses_dept":"econ","courses_title":"process econ dev","courses_id":"441","courses_avg":66.24,"courses_instructor":"","courses_pass":32,"courses_fail":6,"courses_audit":0,"courses_uuid":78459,"courses_year":1900}{"courses_dept":"econ","courses_title":"process econ dev","courses_id":"441","courses_avg":74.4,"courses_instructor":"eswaran, mukesh","courses_pass":27,"courses_fail":3,"courses_audit":0,"courses_uuid":91004,"courses_year":"2013"}{"courses_dept":"econ","courses_title":"process econ dev","courses_id":"441","courses_avg":74.4,"courses_instructor":"","courses_pass":27,"courses_fail":3,"courses_audit":0,"courses_uuid":91005,"courses_year":1900}