{"courses_dept":"civl","courses_title":"concrete techlgy","courses_id":"420","courses_avg":73,"courses_instructor":"zanotti, cristina","courses_pass":7,"courses_fail":0,"courses_audit":0,"courses_uuid":2794,"courses_year":"2015"}{"courses_dept":"civl","courses_title":"concrete techlgy","courses_id":"420","courses_avg":73,"courses_instructor":"","courses_pass":7,"courses_fail":0,"courses_audit":0,"courses_uuid":2795,"courses_year":1900}{"courses_dept":"civl","courses_title":"concrete techlgy","courses_id":"420","courses_avg":81.29,"courses_instructor":"gupta, rishi","courses_pass":20,"courses_fail":1,"courses_audit":0,"courses_uuid":10784,"courses_year":"2009"}{"courses_dept":"civl","courses_title":"concrete techlgy","courses_id":"420","courses_avg":81.29,"courses_instructor":"","courses_pass":20,"courses_fail":1,"courses_audit":0,"courses_uuid":10785,"courses_year":1900}{"courses_dept":"civl","courses_title":"concrete techlgy","courses_id":"420","courses_avg":79.16,"courses_instructor":"","courses_pass":19,"courses_fail":0,"courses_audit":0,"courses_uuid":37631,"courses_year":"2008"}{"courses_dept":"civl","courses_title":"concrete techlgy","courses_id":"420","courses_avg":79.16,"courses_instructor":"","courses_pass":19,"courses_fail":0,"courses_audit":0,"courses_uuid":37632,"courses_year":1900}{"courses_dept":"civl","courses_title":"concrete techlgy","courses_id":"420","courses_avg":75.36,"courses_instructor":"zanotti, cristina","courses_pass":11,"courses_fail":0,"courses_audit":0,"courses_uuid":45067,"courses_year":"2013"}{"courses_dept":"civl","courses_title":"concrete techlgy","courses_id":"420","courses_avg":75.36,"courses_instructor":"","courses_pass":11,"courses_fail":0,"courses_audit":0,"courses_uuid":45068,"courses_year":1900}{"courses_dept":"civl","courses_title":"concrete techlgy","courses_id":"420","courses_avg":80.77,"courses_instructor":"gupta, rishi","courses_pass":13,"courses_fail":0,"courses_audit":0,"courses_uuid":53304,"courses_year":"2010"}{"courses_dept":"civl","courses_title":"concrete techlgy","courses_id":"420","courses_avg":80.77,"courses_instructor":"","courses_pass":13,"courses_fail":0,"courses_audit":0,"courses_uuid":53305,"courses_year":1900}{"courses_dept":"civl","courses_title":"concrete techlgy","courses_id":"420","courses_avg":83.46,"courses_instructor":"gupta, rishi","courses_pass":13,"courses_fail":0,"courses_audit":0,"courses_uuid":79581,"courses_year":"2011"}{"courses_dept":"civl","courses_title":"concrete techlgy","courses_id":"420","courses_avg":83.46,"courses_instructor":"","courses_pass":13,"courses_fail":0,"courses_audit":0,"courses_uuid":79582,"courses_year":1900}