{"courses_dept":"civl","courses_title":"urbn engr m&m","courses_id":"583","courses_avg":92,"courses_instructor":"bigazzi, alexander york","courses_pass":5,"courses_fail":0,"courses_audit":0,"courses_uuid":2892,"courses_year":"2015"}{"courses_dept":"civl","courses_title":"urbn engr m&m","courses_id":"583","courses_avg":92,"courses_instructor":"","courses_pass":5,"courses_fail":0,"courses_audit":0,"courses_uuid":2893,"courses_year":1900}{"courses_dept":"civl","courses_title":"urbn engr m&m","courses_id":"583","courses_avg":72.71,"courses_instructor":"wahba, mohamed","courses_pass":7,"courses_fail":0,"courses_audit":0,"courses_uuid":10860,"courses_year":"2009"}{"courses_dept":"civl","courses_title":"urbn engr m&m","courses_id":"583","courses_avg":72.71,"courses_instructor":"","courses_pass":7,"courses_fail":0,"courses_audit":0,"courses_uuid":10861,"courses_year":1900}{"courses_dept":"civl","courses_title":"urbn engr m&m","courses_id":"583","courses_avg":89.75,"courses_instructor":"lim, clark","courses_pass":12,"courses_fail":0,"courses_audit":0,"courses_uuid":45164,"courses_year":"2013"}{"courses_dept":"civl","courses_title":"urbn engr m&m","courses_id":"583","courses_avg":89.75,"courses_instructor":"","courses_pass":12,"courses_fail":0,"courses_audit":0,"courses_uuid":45165,"courses_year":1900}{"courses_dept":"civl","courses_title":"urbn engr m&m","courses_id":"583","courses_avg":88.5,"courses_instructor":"lim, clark","courses_pass":6,"courses_fail":0,"courses_audit":0,"courses_uuid":48023,"courses_year":"2014"}{"courses_dept":"civl","courses_title":"urbn engr m&m","courses_id":"583","courses_avg":88.5,"courses_instructor":"","courses_pass":6,"courses_fail":0,"courses_audit":0,"courses_uuid":48024,"courses_year":1900}{"courses_dept":"civl","courses_title":"urbn engr m&m","courses_id":"583","courses_avg":84.83,"courses_instructor":"zhao, jinhua","courses_pass":6,"courses_fail":0,"courses_audit":0,"courses_uuid":53392,"courses_year":"2010"}{"courses_dept":"civl","courses_title":"urbn engr m&m","courses_id":"583","courses_avg":84.83,"courses_instructor":"","courses_pass":6,"courses_fail":0,"courses_audit":0,"courses_uuid":53393,"courses_year":1900}{"courses_dept":"civl","courses_title":"urbn engr m&m","courses_id":"583","courses_avg":89.56,"courses_instructor":"zhao, jinhua","courses_pass":9,"courses_fail":0,"courses_audit":0,"courses_uuid":79676,"courses_year":"2011"}{"courses_dept":"civl","courses_title":"urbn engr m&m","courses_id":"583","courses_avg":89.56,"courses_instructor":"","courses_pass":9,"courses_fail":0,"courses_audit":0,"courses_uuid":79677,"courses_year":1900}{"courses_dept":"civl","courses_title":"urbn engr m&m","courses_id":"583","courses_avg":86,"courses_instructor":"zhao, jinhua","courses_pass":4,"courses_fail":0,"courses_audit":0,"courses_uuid":84947,"courses_year":"2012"}{"courses_dept":"civl","courses_title":"urbn engr m&m","courses_id":"583","courses_avg":86,"courses_instructor":"","courses_pass":4,"courses_fail":0,"courses_audit":0,"courses_uuid":84948,"courses_year":1900}