{"courses_dept":"frst","courses_title":"for plant bio i","courses_id":"200","courses_avg":67.5,"courses_instructor":"galvez alcaraz, david","courses_pass":128,"courses_fail":13,"courses_audit":0,"courses_uuid":7316,"courses_year":"2012"}{"courses_dept":"frst","courses_title":"for plant bio i","courses_id":"200","courses_avg":67.5,"courses_instructor":"","courses_pass":128,"courses_fail":13,"courses_audit":0,"courses_uuid":7317,"courses_year":1900}{"courses_dept":"frst","courses_title":"for plant bio i","courses_id":"200","courses_avg":67.57,"courses_instructor":"guy, robert","courses_pass":126,"courses_fail":8,"courses_audit":0,"courses_uuid":21224,"courses_year":"2011"}{"courses_dept":"frst","courses_title":"for plant bio i","courses_id":"200","courses_avg":67.57,"courses_instructor":"","courses_pass":126,"courses_fail":8,"courses_audit":0,"courses_uuid":21225,"courses_year":1900}{"courses_dept":"frst","courses_title":"for plant bio i","courses_id":"200","courses_avg":67.48,"courses_instructor":"guy, robert","courses_pass":90,"courses_fail":11,"courses_audit":0,"courses_uuid":34868,"courses_year":"2010"}{"courses_dept":"frst","courses_title":"for plant bio i","courses_id":"200","courses_avg":67.48,"courses_instructor":"","courses_pass":90,"courses_fail":11,"courses_audit":0,"courses_uuid":34869,"courses_year":1900}{"courses_dept":"frst","courses_title":"for plant bio i","courses_id":"200","courses_avg":70.46,"courses_instructor":"guy, robert","courses_pass":170,"courses_fail":3,"courses_audit":0,"courses_uuid":54898,"courses_year":"2015"}{"courses_dept":"frst","courses_title":"for plant bio i","courses_id":"200","courses_avg":70.46,"courses_instructor":"","courses_pass":170,"courses_fail":3,"courses_audit":0,"courses_uuid":54899,"courses_year":1900}{"courses_dept":"frst","courses_title":"for plant bio i","courses_id":"200","courses_avg":64.06,"courses_instructor":"","courses_pass":87,"courses_fail":9,"courses_audit":0,"courses_uuid":59649,"courses_year":"2008"}{"courses_dept":"frst","courses_title":"for plant bio i","courses_id":"200","courses_avg":64.06,"courses_instructor":"","courses_pass":87,"courses_fail":9,"courses_audit":0,"courses_uuid":59650,"courses_year":1900}{"courses_dept":"frst","courses_title":"for plant bio i","courses_id":"200","courses_avg":70.25,"courses_instructor":"guy, robert","courses_pass":165,"courses_fail":6,"courses_audit":0,"courses_uuid":86549,"courses_year":"2014"}{"courses_dept":"frst","courses_title":"for plant bio i","courses_id":"200","courses_avg":70.25,"courses_instructor":"","courses_pass":165,"courses_fail":6,"courses_audit":0,"courses_uuid":86550,"courses_year":1900}{"courses_dept":"frst","courses_title":"for plant bio i","courses_id":"200","courses_avg":66.42,"courses_instructor":"aitken, sally;guy, robert","courses_pass":90,"courses_fail":9,"courses_audit":0,"courses_uuid":89532,"courses_year":"2007"}{"courses_dept":"frst","courses_title":"for plant bio i","courses_id":"200","courses_avg":66.42,"courses_instructor":"","courses_pass":90,"courses_fail":9,"courses_audit":0,"courses_uuid":89533,"courses_year":1900}{"courses_dept":"frst","courses_title":"for plant bio i","courses_id":"200","courses_avg":66.51,"courses_instructor":"guy, robert","courses_pass":129,"courses_fail":9,"courses_audit":0,"courses_uuid":97629,"courses_year":"2013"}{"courses_dept":"frst","courses_title":"for plant bio i","courses_id":"200","courses_avg":66.51,"courses_instructor":"","courses_pass":129,"courses_fail":9,"courses_audit":0,"courses_uuid":97630,"courses_year":1900}