{"courses_dept":"chin","courses_title":"ad chin sp&wr ii","courses_id":"307","courses_avg":80.33,"courses_instructor":"li, duanduan","courses_pass":12,"courses_fail":0,"courses_audit":0,"courses_uuid":2093,"courses_year":"2009"}{"courses_dept":"chin","courses_title":"ad chin sp&wr ii","courses_id":"307","courses_avg":80.33,"courses_instructor":"","courses_pass":12,"courses_fail":0,"courses_audit":0,"courses_uuid":2094,"courses_year":1900}{"courses_dept":"chin","courses_title":"ad chin sp&wr ii","courses_id":"307","courses_avg":80.11,"courses_instructor":"li, duanduan","courses_pass":9,"courses_fail":0,"courses_audit":0,"courses_uuid":9469,"courses_year":"2012"}{"courses_dept":"chin","courses_title":"ad chin sp&wr ii","courses_id":"307","courses_avg":80.11,"courses_instructor":"","courses_pass":9,"courses_fail":0,"courses_audit":0,"courses_uuid":9470,"courses_year":1900}{"courses_dept":"chin","courses_title":"ad chin sp&wr ii","courses_id":"307","courses_avg":81.45,"courses_instructor":"li, duanduan","courses_pass":11,"courses_fail":0,"courses_audit":0,"courses_uuid":23262,"courses_year":"2014"}{"courses_dept":"chin","courses_title":"ad chin sp&wr ii","courses_id":"307","courses_avg":81.45,"courses_instructor":"","courses_pass":11,"courses_fail":0,"courses_audit":0,"courses_uuid":23263,"courses_year":1900}{"courses_dept":"chin","courses_title":"ad chin sp&wr ii","courses_id":"307","courses_avg":76,"courses_instructor":"wu, xinxin","courses_pass":10,"courses_fail":0,"courses_audit":0,"courses_uuid":30780,"courses_year":"2010"}{"courses_dept":"chin","courses_title":"ad chin sp&wr ii","courses_id":"307","courses_avg":76,"courses_instructor":"","courses_pass":10,"courses_fail":0,"courses_audit":0,"courses_uuid":30781,"courses_year":1900}{"courses_dept":"chin","courses_title":"ad chin sp&wr ii","courses_id":"307","courses_avg":75.33,"courses_instructor":"","courses_pass":18,"courses_fail":0,"courses_audit":0,"courses_uuid":35769,"courses_year":"2008"}{"courses_dept":"chin","courses_title":"ad chin sp&wr ii","courses_id":"307","courses_avg":75.33,"courses_instructor":"","courses_pass":18,"courses_fail":0,"courses_audit":0,"courses_uuid":35770,"courses_year":1900}{"courses_dept":"chin","courses_title":"ad chin sp&wr ii","courses_id":"307","courses_avg":79,"courses_instructor":"li, duanduan","courses_pass":18,"courses_fail":0,"courses_audit":0,"courses_uuid":66335,"courses_year":"2015"}{"courses_dept":"chin","courses_title":"ad chin sp&wr ii","courses_id":"307","courses_avg":79,"courses_instructor":"","courses_pass":18,"courses_fail":0,"courses_audit":0,"courses_uuid":66336,"courses_year":1900}{"courses_dept":"chin","courses_title":"ad chin sp&wr ii","courses_id":"307","courses_avg":79,"courses_instructor":"li, duanduan","courses_pass":14,"courses_fail":0,"courses_audit":0,"courses_uuid":73403,"courses_year":"2011"}{"courses_dept":"chin","courses_title":"ad chin sp&wr ii","courses_id":"307","courses_avg":79,"courses_instructor":"","courses_pass":14,"courses_fail":0,"courses_audit":0,"courses_uuid":73404,"courses_year":1900}{"courses_dept":"chin","courses_title":"ad chin sp&wr ii","courses_id":"307","courses_avg":76.61,"courses_instructor":"wu, xinxin","courses_pass":18,"courses_fail":0,"courses_audit":0,"courses_uuid":83208,"courses_year":"2013"}{"courses_dept":"chin","courses_title":"ad chin sp&wr ii","courses_id":"307","courses_avg":76.61,"courses_instructor":"","courses_pass":18,"courses_fail":0,"courses_audit":0,"courses_uuid":83209,"courses_year":1900}