{"courses_dept":"cpsc","courses_title":"comp comm protcl","courses_id":"527","courses_avg":83.78,"courses_instructor":"vuong, son","courses_pass":23,"courses_fail":0,"courses_audit":0,"courses_uuid":46784,"courses_year":"2009"}{"courses_dept":"cpsc","courses_title":"comp comm protcl","courses_id":"527","courses_avg":83.78,"courses_instructor":"","courses_pass":23,"courses_fail":0,"courses_audit":0,"courses_uuid":46785,"courses_year":1900}{"courses_dept":"cpsc","courses_title":"comp comm protcl","courses_id":"527","courses_avg":84.83,"courses_instructor":"","courses_pass":18,"courses_fail":0,"courses_audit":1,"courses_uuid":52096,"courses_year":"2008"}{"courses_dept":"cpsc","courses_title":"comp comm protcl","courses_id":"527","courses_avg":84.83,"courses_instructor":"","courses_pass":18,"courses_fail":0,"courses_audit":1,"courses_uuid":52097,"courses_year":1900}{"courses_dept":"cpsc","courses_title":"comp comm protcl","courses_id":"527","courses_avg":91.22,"courses_instructor":"beschastnikh, ivan","courses_pass":9,"courses_fail":0,"courses_audit":1,"courses_uuid":62468,"courses_year":"2015"}{"courses_dept":"cpsc","courses_title":"comp comm protcl","courses_id":"527","courses_avg":91.22,"courses_instructor":"","courses_pass":9,"courses_fail":0,"courses_audit":1,"courses_uuid":62469,"courses_year":1900}{"courses_dept":"cpsc","courses_title":"comp comm protcl","courses_id":"527","courses_avg":90.11,"courses_instructor":"krasic, charles","courses_pass":9,"courses_fail":0,"courses_audit":1,"courses_uuid":90629,"courses_year":"2007"}{"courses_dept":"cpsc","courses_title":"comp comm protcl","courses_id":"527","courses_avg":90.11,"courses_instructor":"","courses_pass":9,"courses_fail":0,"courses_audit":1,"courses_uuid":90630,"courses_year":1900}