{"courses_dept":"crwr","courses_title":"intr writ poetry","courses_id":"201","courses_avg":73.33,"courses_instructor":"warrener, sheryda","courses_pass":120,"courses_fail":7,"courses_audit":0,"courses_uuid":26131,"courses_year":"2014"}{"courses_dept":"crwr","courses_title":"intr writ poetry","courses_id":"201","courses_avg":73.33,"courses_instructor":"","courses_pass":120,"courses_fail":7,"courses_audit":0,"courses_uuid":26132,"courses_year":1900}{"courses_dept":"crwr","courses_title":"intr writ poetry","courses_id":"201","courses_avg":76.02,"courses_instructor":"warrener, sheryda","courses_pass":127,"courses_fail":5,"courses_audit":1,"courses_uuid":50507,"courses_year":"2016"}{"courses_dept":"crwr","courses_title":"intr writ poetry","courses_id":"201","courses_avg":76.02,"courses_instructor":"","courses_pass":127,"courses_fail":5,"courses_audit":2,"courses_uuid":50508,"courses_year":1900}{"courses_dept":"crwr","courses_title":"intr writ poetry","courses_id":"201","courses_avg":73.32,"courses_instructor":"warrener, sheryda","courses_pass":113,"courses_fail":4,"courses_audit":2,"courses_uuid":75025,"courses_year":"2015"}{"courses_dept":"crwr","courses_title":"intr writ poetry","courses_id":"201","courses_avg":78.71,"courses_instructor":"warrener, sheryda","courses_pass":95,"courses_fail":4,"courses_audit":0,"courses_uuid":75026,"courses_year":"2015"}{"courses_dept":"crwr","courses_title":"intr writ poetry","courses_id":"201","courses_avg":75.79,"courses_instructor":"","courses_pass":208,"courses_fail":8,"courses_audit":2,"courses_uuid":75027,"courses_year":1900}